mlem/__init__.py
mlem/dataset.py
mlem/dectree.py
mlem/utils.py
mlem_py-0.2.1.dist-info/LICENSE
mlem_py-0.2.1.dist-info/METADATA
mlem_py-0.2.1.dist-info/WHEEL
mlem_py-0.2.1.dist-info/top_level.txt
mlem_py-0.2.1.dist-info/RECORD
