Metadata-Version: 2.1
Name: mlem-py
Version: 0.2.1
Summary: Pure Python machine learning library
Author: atzur
Project-URL: homepage, https://github.com/atzuur/mlem
Classifier: Programming Language :: Python :: 3
Classifier: License :: OSI Approved :: MIT License
Classifier: Operating System :: OS Independent
Requires-Python: >=3.9
License-File: LICENSE
Requires-Dist: pydot
